{"wallet":"0xc89b061b18fa3d37470a017d3d3bc12ecf42f4b1","rank":112510,"lifetime":{"months_active":23,"first":"2023-07","last":"2025-10","tx_sum":434,"uniq_sum":244,"trade_sum":37,"nft_sum":68,"gas_sum":0.007752,"avg_balance_eth_mean":0.003005,"streak_best_days":0,"gas_sum_filled":0.007752},"months":{"2023-07":{"txs":0,"uniq":0,"trade":0,"nft":0,"gas":0,"bal":0,"days":0,"spread":0,"streak":0,"rank_m":243856,"pct_m":0.259271},"2023-08":{"txs":9,"uniq":6,"trade":0,"nft":5,"gas":0.002409,"bal":0.001077,"days":4,"spread":0.129032,"streak":0,"rank_m":111638,"pct_m":0.118694,"gas_method":"exact"},"2023-09":{"txs":0,"uniq":0,"trade":0,"nft":0,"gas":0,"bal":0.001077,"days":0,"spread":0,"streak":0,"rank_m":177236,"pct_m":0.188439},"2023-10":{"txs":0,"uniq":0,"trade":0,"nft":0,"gas":0,"bal":0.001077,"days":0,"spread":0,"streak":0,"rank_m":177450,"pct_m":0.188667},"2023-11":{"txs":46,"uniq":26,"trade":2,"nft":16,"gas":0.003239,"bal":0.000599,"days":3,"spread":0.1,"streak":0,"rank_m":65833,"pct_m":0.069994,"gas_method":"exact"},"2023-12":{"txs":0,"uniq":0,"trade":0,"nft":0,"gas":0,"bal":0.000599,"days":0,"spread":0,"streak":0,"rank_m":220840,"pct_m":0.2348},"2024-01":{"txs":1,"uniq":1,"trade":0,"nft":1,"gas":0.000027,"bal":0.000075,"days":1,"spread":0.032258,"streak":0,"rank_m":193391,"pct_m":0.205616,"gas_method":"exact"},"2024-02":{"txs":18,"uniq":13,"trade":0,"nft":9,"gas":0.000169,"bal":0.000074,"days":5,"spread":0.172414,"streak":0,"rank_m":182340,"pct_m":0.193866,"gas_method":"estimated"},"2024-03":{"txs":13,"uniq":7,"trade":0,"nft":4,"gas":0.000184,"bal":0.000616,"days":5,"spread":0.16129,"streak":0,"rank_m":264044,"pct_m":0.280735,"gas_method":"estimated"},"2024-04":{"txs":19,"uniq":12,"trade":0,"nft":4,"gas":0.000033,"bal":0.000643,"days":6,"spread":0.2,"streak":0,"rank_m":337049,"pct_m":0.358355,"gas_method":"estimated"},"2024-05":{"txs":83,"uniq":27,"trade":3,"nft":7,"gas":0.000002,"bal":0.002275,"days":22,"spread":0.709677,"streak":0,"rank_m":97125,"pct_m":0.103264,"gas_method":"exact"},"2024-06":{"txs":28,"uniq":15,"trade":0,"nft":5,"gas":0,"bal":0.001456,"days":11,"spread":0.366667,"streak":0,"rank_m":166615,"pct_m":0.177147,"gas_method":"exact"},"2024-07":{"txs":0,"uniq":0,"trade":0,"nft":0,"gas":0,"bal":0.001456,"days":0,"spread":0,"streak":0,"rank_m":531925,"pct_m":0.565551},"2024-08":{"txs":4,"uniq":3,"trade":0,"nft":2,"gas":0,"bal":0.000944,"days":1,"spread":0.032258,"streak":0,"rank_m":454114,"pct_m":0.482821,"gas_method":"estimated"},"2024-09":{"txs":14,"uniq":12,"trade":0,"nft":11,"gas":0.000004,"bal":0.000237,"days":4,"spread":0.133333,"streak":0,"rank_m":213739,"pct_m":0.22725,"gas_method":"exact"},"2024-10":{"txs":6,"uniq":4,"trade":13,"nft":1,"gas":0,"bal":0.000225,"days":5,"spread":0.16129,"streak":0,"rank_m":390680,"pct_m":0.415377,"gas_method":"estimated"},"2024-11":{"txs":35,"uniq":18,"trade":2,"nft":2,"gas":0.000078,"bal":0.000654,"days":10,"spread":0.333333,"streak":0,"rank_m":190502,"pct_m":0.202544,"gas_method":"exact"},"2024-12":{"txs":25,"uniq":17,"trade":0,"nft":1,"gas":0.000551,"bal":0.004537,"days":8,"spread":0.258065,"streak":0,"rank_m":209244,"pct_m":0.222471,"gas_method":"exact"},"2025-01":{"txs":21,"uniq":11,"trade":0,"nft":0,"gas":0.000546,"bal":0.002734,"days":7,"spread":0.225806,"streak":0,"rank_m":248691,"pct_m":0.264412,"gas_method":"exact"},"2025-02":{"txs":5,"uniq":4,"trade":0,"nft":0,"gas":0.000028,"bal":0.006487,"days":4,"spread":0.142857,"streak":0,"rank_m":339104,"pct_m":0.36054,"gas_method":"exact"},"2025-03":{"txs":15,"uniq":9,"trade":0,"nft":0,"gas":0.000079,"bal":0.022614,"days":4,"spread":0.129032,"streak":0,"rank_m":198778,"pct_m":0.211343,"gas_method":"exact"},"2025-04":{"txs":35,"uniq":24,"trade":7,"nft":0,"gas":0.000003,"bal":0.027099,"days":9,"spread":0.3,"streak":0,"rank_m":112539,"pct_m":0.119652,"gas_method":"exact"},"2025-05":{"txs":39,"uniq":22,"trade":10,"nft":0,"gas":0.000274,"bal":0.007497,"days":7,"spread":0.225806,"streak":0,"rank_m":85876,"pct_m":0.091304,"gas_method":"estimated"},"2025-06":{"txs":12,"uniq":12,"trade":0,"nft":0,"gas":0.000084,"bal":0.000085,"days":2,"spread":0.066667,"streak":0,"rank_m":580815,"pct_m":0.617532,"gas_method":"estimated"},"2025-07":{"txs":1,"uniq":0,"trade":0,"nft":0,"gas":0.000007,"bal":0,"days":1,"spread":0.032258,"streak":0,"rank_m":823493,"pct_m":0.875551,"gas_method":"estimated"},"2025-08":{"txs":1,"uniq":1,"trade":0,"nft":0,"gas":0.000007,"bal":0,"days":1,"spread":0.032258,"streak":0,"rank_m":753613,"pct_m":0.801254,"gas_method":"estimated"},"2025-09":{"txs":2,"uniq":0,"trade":0,"nft":0,"gas":0.000014,"bal":0,"days":2,"spread":0.066667,"streak":0,"rank_m":790208,"pct_m":0.840162,"gas_method":"estimated"},"2025-10":{"txs":2,"uniq":0,"trade":0,"nft":0,"gas":0.000014,"bal":0,"days":2,"spread":0.064516,"streak":0,"rank_m":721581,"pct_m":0.767197,"gas_method":"estimated"}}}