{"wallet":"0xc12458da99d9baac12b9aa20cc82456cec71e575","rank":363426,"lifetime":{"months_active":9,"first":"2023-07","last":"2025-10","tx_sum":596,"uniq_sum":284,"trade_sum":0,"nft_sum":414,"gas_sum":0.000365,"avg_balance_eth_mean":0.000127,"streak_best_days":41,"gas_sum_filled":0.000365},"months":{"2023-07":{"txs":0,"uniq":0,"trade":0,"nft":0,"gas":0,"bal":0,"days":0,"spread":0,"streak":0,"rank_m":269506,"pct_m":0.286543},"2023-08":{"txs":0,"uniq":0,"trade":0,"nft":0,"gas":0,"bal":0,"days":0,"spread":0,"streak":0,"rank_m":356311,"pct_m":0.378835},"2023-09":{"txs":0,"uniq":0,"trade":0,"nft":0,"gas":0,"bal":0,"days":0,"spread":0,"streak":0,"rank_m":377821,"pct_m":0.401705},"2023-10":{"txs":0,"uniq":0,"trade":0,"nft":0,"gas":0,"bal":0,"days":0,"spread":0,"streak":0,"rank_m":395859,"pct_m":0.420883},"2023-11":{"txs":0,"uniq":0,"trade":0,"nft":0,"gas":0,"bal":0,"days":0,"spread":0,"streak":0,"rank_m":412018,"pct_m":0.438064},"2023-12":{"txs":0,"uniq":0,"trade":0,"nft":0,"gas":0,"bal":0,"days":0,"spread":0,"streak":0,"rank_m":431898,"pct_m":0.459201},"2024-01":{"txs":0,"uniq":0,"trade":0,"nft":0,"gas":0,"bal":0,"days":0,"spread":0,"streak":0,"rank_m":449005,"pct_m":0.477389},"2024-02":{"txs":0,"uniq":0,"trade":0,"nft":0,"gas":0,"bal":0,"days":0,"spread":0,"streak":0,"rank_m":488724,"pct_m":0.519619},"2024-03":{"txs":0,"uniq":0,"trade":0,"nft":0,"gas":0,"bal":0,"days":0,"spread":0,"streak":0,"rank_m":551883,"pct_m":0.586771},"2024-04":{"txs":0,"uniq":0,"trade":0,"nft":0,"gas":0,"bal":0,"days":0,"spread":0,"streak":0,"rank_m":611907,"pct_m":0.650589},"2024-05":{"txs":0,"uniq":0,"trade":0,"nft":0,"gas":0,"bal":0,"days":0,"spread":0,"streak":0,"rank_m":643930,"pct_m":0.684637},"2024-06":{"txs":186,"uniq":91,"trade":0,"nft":154,"gas":0.000001,"bal":0.000024,"days":23,"spread":0.766667,"streak":23,"rank_m":140375,"pct_m":0.149248,"gas_method":"estimated"},"2024-07":{"txs":118,"uniq":55,"trade":0,"nft":97,"gas":0.000008,"bal":0.000032,"days":21,"spread":0.677419,"streak":18,"rank_m":56131,"pct_m":0.059678,"gas_method":"exact"},"2024-08":{"txs":86,"uniq":49,"trade":0,"nft":73,"gas":0.000001,"bal":0.000075,"days":20,"spread":0.645161,"streak":11,"rank_m":152304,"pct_m":0.161931,"gas_method":"estimated"},"2024-09":{"txs":142,"uniq":57,"trade":0,"nft":70,"gas":0.000001,"bal":0.000309,"days":26,"spread":0.866667,"streak":12,"rank_m":42575,"pct_m":0.045265,"gas_method":"exact"},"2024-10":{"txs":42,"uniq":17,"trade":0,"nft":20,"gas":0.000002,"bal":0.000247,"days":19,"spread":0.612903,"streak":6,"rank_m":89849,"pct_m":0.095528,"gas_method":"exact"},"2024-11":{"txs":3,"uniq":2,"trade":0,"nft":0,"gas":0.000005,"bal":0.000231,"days":1,"spread":0.033333,"streak":1,"rank_m":476403,"pct_m":0.506519,"gas_method":"exact"},"2024-12":{"txs":3,"uniq":3,"trade":0,"nft":0,"gas":0.000066,"bal":0.000229,"days":3,"spread":0.096774,"streak":1,"rank_m":507182,"pct_m":0.539244,"gas_method":"exact"},"2025-01":{"txs":13,"uniq":8,"trade":0,"nft":0,"gas":0.00026,"bal":0.000124,"days":5,"spread":0.16129,"streak":2,"rank_m":337172,"pct_m":0.358486,"gas_method":"exact"},"2025-02":{"txs":0,"uniq":0,"trade":0,"nft":0,"gas":0,"bal":0.000124,"days":0,"spread":0,"streak":0,"rank_m":722249,"pct_m":0.767907},"2025-03":{"txs":0,"uniq":0,"trade":0,"nft":0,"gas":0,"bal":0.000124,"days":0,"spread":0,"streak":0,"rank_m":732272,"pct_m":0.778564},"2025-04":{"txs":0,"uniq":0,"trade":0,"nft":0,"gas":0,"bal":0.000124,"days":0,"spread":0,"streak":0,"rank_m":757352,"pct_m":0.805229},"2025-05":{"txs":3,"uniq":2,"trade":0,"nft":0,"gas":0.000021,"bal":0.000319,"days":2,"spread":0.064516,"streak":1,"rank_m":534589,"pct_m":0.568384,"gas_method":"estimated"},"2025-06":{"txs":0,"uniq":0,"trade":0,"nft":0,"gas":0,"bal":0.000319,"days":0,"spread":0,"streak":0,"rank_m":736338,"pct_m":0.782887},"2025-07":{"txs":0,"uniq":0,"trade":0,"nft":0,"gas":0,"bal":0.000319,"days":0,"spread":0,"streak":0,"rank_m":758954,"pct_m":0.806932},"2025-08":{"txs":0,"uniq":0,"trade":0,"nft":0,"gas":0,"bal":0.000319,"days":0,"spread":0,"streak":0,"rank_m":736574,"pct_m":0.783138},"2025-09":{"txs":0,"uniq":0,"trade":0,"nft":0,"gas":0,"bal":0.000319,"days":0,"spread":0,"streak":0,"rank_m":724974,"pct_m":0.770804},"2025-10":{"txs":0,"uniq":0,"trade":0,"nft":0,"gas":0,"bal":0.000319,"days":0,"spread":0,"streak":0,"rank_m":649340,"pct_m":0.690389}}}