{"wallet":"0xce058c9952876060e2c2ea9eabbbb3a65adfc5c9","rank":936196,"lifetime":{"months_active":3,"first":"2023-07","last":"2025-10","tx_sum":126,"uniq_sum":24,"trade_sum":0,"nft_sum":0,"gas_sum":0.000004,"avg_balance_eth_mean":0.000412,"streak_best_days":5,"gas_sum_filled":0.000004},"months":{"2023-07":{"txs":0,"uniq":0,"trade":0,"nft":0,"gas":0,"bal":0,"days":0,"spread":0,"streak":0,"rank_m":225159,"pct_m":0.239392},"2023-08":{"txs":0,"uniq":0,"trade":0,"nft":0,"gas":0,"bal":0,"days":0,"spread":0,"streak":0,"rank_m":317183,"pct_m":0.337234},"2023-09":{"txs":0,"uniq":0,"trade":0,"nft":0,"gas":0,"bal":0,"days":0,"spread":0,"streak":0,"rank_m":334562,"pct_m":0.355711},"2023-10":{"txs":0,"uniq":0,"trade":0,"nft":0,"gas":0,"bal":0,"days":0,"spread":0,"streak":0,"rank_m":352967,"pct_m":0.37528},"2023-11":{"txs":0,"uniq":0,"trade":0,"nft":0,"gas":0,"bal":0,"days":0,"spread":0,"streak":0,"rank_m":369643,"pct_m":0.39301},"2023-12":{"txs":0,"uniq":0,"trade":0,"nft":0,"gas":0,"bal":0,"days":0,"spread":0,"streak":0,"rank_m":391482,"pct_m":0.41623},"2024-01":{"txs":0,"uniq":0,"trade":0,"nft":0,"gas":0,"bal":0,"days":0,"spread":0,"streak":0,"rank_m":408777,"pct_m":0.434618},"2024-02":{"txs":0,"uniq":0,"trade":0,"nft":0,"gas":0,"bal":0,"days":0,"spread":0,"streak":0,"rank_m":453552,"pct_m":0.482224},"2024-03":{"txs":0,"uniq":0,"trade":0,"nft":0,"gas":0,"bal":0,"days":0,"spread":0,"streak":0,"rank_m":522628,"pct_m":0.555666},"2024-04":{"txs":0,"uniq":0,"trade":0,"nft":0,"gas":0,"bal":0,"days":0,"spread":0,"streak":0,"rank_m":587521,"pct_m":0.624662},"2024-05":{"txs":0,"uniq":0,"trade":0,"nft":0,"gas":0,"bal":0,"days":0,"spread":0,"streak":0,"rank_m":620811,"pct_m":0.660056},"2024-06":{"txs":55,"uniq":7,"trade":0,"nft":0,"gas":0,"bal":0.001176,"days":9,"spread":0.3,"streak":3,"rank_m":249052,"pct_m":0.264795,"gas_method":"estimated"},"2024-07":{"txs":70,"uniq":16,"trade":0,"nft":0,"gas":0.000004,"bal":0.001885,"days":18,"spread":0.580645,"streak":5,"rank_m":76044,"pct_m":0.08085,"gas_method":"exact"},"2024-08":{"txs":0,"uniq":0,"trade":0,"nft":0,"gas":0,"bal":0.001885,"days":0,"spread":0,"streak":0,"rank_m":535316,"pct_m":0.569156},"2024-09":{"txs":0,"uniq":0,"trade":0,"nft":0,"gas":0,"bal":0.001885,"days":0,"spread":0,"streak":0,"rank_m":511837,"pct_m":0.544193},"2024-10":{"txs":1,"uniq":1,"trade":0,"nft":0,"gas":0,"bal":0.000362,"days":1,"spread":0.032258,"streak":1,"rank_m":532252,"pct_m":0.565899,"gas_method":"estimated"},"2024-11":{"txs":0,"uniq":0,"trade":0,"nft":0,"gas":0,"bal":0.000362,"days":0,"spread":0,"streak":0,"rank_m":622924,"pct_m":0.662303},"2024-12":{"txs":0,"uniq":0,"trade":0,"nft":0,"gas":0,"bal":0.000362,"days":0,"spread":0,"streak":0,"rank_m":669871,"pct_m":0.712218},"2025-01":{"txs":0,"uniq":0,"trade":0,"nft":0,"gas":0,"bal":0.000362,"days":0,"spread":0,"streak":0,"rank_m":667248,"pct_m":0.709429},"2025-02":{"txs":0,"uniq":0,"trade":0,"nft":0,"gas":0,"bal":0.000362,"days":0,"spread":0,"streak":0,"rank_m":687825,"pct_m":0.731307},"2025-03":{"txs":0,"uniq":0,"trade":0,"nft":0,"gas":0,"bal":0.000362,"days":0,"spread":0,"streak":0,"rank_m":691915,"pct_m":0.735655},"2025-04":{"txs":0,"uniq":0,"trade":0,"nft":0,"gas":0,"bal":0.000362,"days":0,"spread":0,"streak":0,"rank_m":718853,"pct_m":0.764296},"2025-05":{"txs":0,"uniq":0,"trade":0,"nft":0,"gas":0,"bal":0.000362,"days":0,"spread":0,"streak":0,"rank_m":728997,"pct_m":0.775082},"2025-06":{"txs":0,"uniq":0,"trade":0,"nft":0,"gas":0,"bal":0.000362,"days":0,"spread":0,"streak":0,"rank_m":725711,"pct_m":0.771588},"2025-07":{"txs":0,"uniq":0,"trade":0,"nft":0,"gas":0,"bal":0.000362,"days":0,"spread":0,"streak":0,"rank_m":747700,"pct_m":0.794967},"2025-08":{"txs":0,"uniq":0,"trade":0,"nft":0,"gas":0,"bal":0.000362,"days":0,"spread":0,"streak":0,"rank_m":724937,"pct_m":0.770765},"2025-09":{"txs":0,"uniq":0,"trade":0,"nft":0,"gas":0,"bal":0.000362,"days":0,"spread":0,"streak":0,"rank_m":708794,"pct_m":0.753601},"2025-10":{"txs":0,"uniq":0,"trade":0,"nft":0,"gas":0,"bal":0.000362,"days":0,"spread":0,"streak":0,"rank_m":633153,"pct_m":0.673179}}}