{"wallet":"0xc2237ae7fab6946b2842bd0b773ea015b0ad4f02","rank":661263,"lifetime":{"months_active":7,"first":"2023-07","last":"2025-10","tx_sum":353,"uniq_sum":54,"trade_sum":1,"nft_sum":2,"gas_sum":0.002473,"avg_balance_eth_mean":0.000626,"streak_best_days":19,"gas_sum_filled":0.002473},"months":{"2023-07":{"txs":0,"uniq":0,"trade":0,"nft":0,"gas":0,"bal":0,"days":0,"spread":0,"streak":0,"rank_m":266105,"pct_m":0.282927},"2023-08":{"txs":0,"uniq":0,"trade":0,"nft":0,"gas":0,"bal":0,"days":0,"spread":0,"streak":0,"rank_m":353340,"pct_m":0.375676},"2023-09":{"txs":0,"uniq":0,"trade":0,"nft":0,"gas":0,"bal":0,"days":0,"spread":0,"streak":0,"rank_m":374652,"pct_m":0.398336},"2023-10":{"txs":0,"uniq":0,"trade":0,"nft":0,"gas":0,"bal":0,"days":0,"spread":0,"streak":0,"rank_m":392700,"pct_m":0.417525},"2023-11":{"txs":0,"uniq":0,"trade":0,"nft":0,"gas":0,"bal":0,"days":0,"spread":0,"streak":0,"rank_m":408904,"pct_m":0.434753},"2023-12":{"txs":0,"uniq":0,"trade":0,"nft":0,"gas":0,"bal":0,"days":0,"spread":0,"streak":0,"rank_m":428882,"pct_m":0.455994},"2024-01":{"txs":0,"uniq":0,"trade":0,"nft":0,"gas":0,"bal":0,"days":0,"spread":0,"streak":0,"rank_m":446025,"pct_m":0.474221},"2024-02":{"txs":0,"uniq":0,"trade":0,"nft":0,"gas":0,"bal":0,"days":0,"spread":0,"streak":0,"rank_m":486105,"pct_m":0.516834},"2024-03":{"txs":0,"uniq":0,"trade":0,"nft":0,"gas":0,"bal":0,"days":0,"spread":0,"streak":0,"rank_m":549664,"pct_m":0.584412},"2024-04":{"txs":0,"uniq":0,"trade":0,"nft":0,"gas":0,"bal":0,"days":0,"spread":0,"streak":0,"rank_m":610023,"pct_m":0.648586},"2024-05":{"txs":0,"uniq":0,"trade":0,"nft":0,"gas":0,"bal":0,"days":0,"spread":0,"streak":0,"rank_m":642131,"pct_m":0.682724},"2024-06":{"txs":0,"uniq":0,"trade":0,"nft":0,"gas":0,"bal":0,"days":0,"spread":0,"streak":0,"rank_m":669317,"pct_m":0.711629},"2024-07":{"txs":0,"uniq":0,"trade":0,"nft":0,"gas":0,"bal":0,"days":0,"spread":0,"streak":0,"rank_m":691454,"pct_m":0.735165},"2024-08":{"txs":0,"uniq":0,"trade":0,"nft":0,"gas":0,"bal":0,"days":0,"spread":0,"streak":0,"rank_m":709939,"pct_m":0.754819},"2024-09":{"txs":0,"uniq":0,"trade":0,"nft":0,"gas":0,"bal":0,"days":0,"spread":0,"streak":0,"rank_m":722267,"pct_m":0.767926},"2024-10":{"txs":0,"uniq":0,"trade":0,"nft":0,"gas":0,"bal":0,"days":0,"spread":0,"streak":0,"rank_m":746186,"pct_m":0.793357},"2024-11":{"txs":0,"uniq":0,"trade":0,"nft":0,"gas":0,"bal":0,"days":0,"spread":0,"streak":0,"rank_m":761133,"pct_m":0.809249},"2024-12":{"txs":0,"uniq":0,"trade":0,"nft":0,"gas":0,"bal":0,"days":0,"spread":0,"streak":0,"rank_m":787785,"pct_m":0.837586},"2025-01":{"txs":0,"uniq":0,"trade":0,"nft":0,"gas":0,"bal":0,"days":0,"spread":0,"streak":0,"rank_m":803534,"pct_m":0.854331},"2025-02":{"txs":0,"uniq":0,"trade":0,"nft":0,"gas":0,"bal":0,"days":0,"spread":0,"streak":0,"rank_m":822604,"pct_m":0.874606},"2025-03":{"txs":0,"uniq":0,"trade":0,"nft":0,"gas":0,"bal":0,"days":0,"spread":0,"streak":0,"rank_m":838039,"pct_m":0.891017},"2025-04":{"txs":5,"uniq":3,"trade":0,"nft":0,"gas":0.000024,"bal":0.000047,"days":2,"spread":0.066667,"streak":1,"rank_m":460704,"pct_m":0.489828,"gas_method":"exact"},"2025-05":{"txs":24,"uniq":12,"trade":0,"nft":0,"gas":0.000169,"bal":0.004505,"days":5,"spread":0.16129,"streak":1,"rank_m":163311,"pct_m":0.173634,"gas_method":"estimated"},"2025-06":{"txs":57,"uniq":2,"trade":0,"nft":0,"gas":0.000401,"bal":0.00483,"days":2,"spread":0.066667,"streak":1,"rank_m":285400,"pct_m":0.303441,"gas_method":"estimated"},"2025-07":{"txs":7,"uniq":4,"trade":0,"nft":1,"gas":0.000049,"bal":0.004301,"days":3,"spread":0.096774,"streak":1,"rank_m":299239,"pct_m":0.318155,"gas_method":"estimated"},"2025-08":{"txs":5,"uniq":5,"trade":0,"nft":0,"gas":0.000035,"bal":0.003083,"days":4,"spread":0.129032,"streak":1,"rank_m":338983,"pct_m":0.360412,"gas_method":"estimated"},"2025-09":{"txs":228,"uniq":27,"trade":1,"nft":0,"gas":0.001605,"bal":0.000326,"days":20,"spread":0.666667,"streak":11,"rank_m":124838,"pct_m":0.132729,"gas_method":"estimated"},"2025-10":{"txs":27,"uniq":1,"trade":0,"nft":1,"gas":0.00019,"bal":0.00044,"days":9,"spread":0.290323,"streak":8,"rank_m":201464,"pct_m":0.214199,"gas_method":"estimated"}}}