{"wallet":"0xc2c8cb5f1bdc83b2d073ca88c9374e86d11b0fd1","rank":591166,"lifetime":{"months_active":7,"first":"2023-07","last":"2025-10","tx_sum":367,"uniq_sum":109,"trade_sum":0,"nft_sum":0,"gas_sum":0.002487,"avg_balance_eth_mean":0.000083,"streak_best_days":23,"gas_sum_filled":0.002487},"months":{"2023-07":{"txs":0,"uniq":0,"trade":0,"nft":0,"gas":0,"bal":0,"days":0,"spread":0,"streak":0,"rank_m":263865,"pct_m":0.280545},"2023-08":{"txs":0,"uniq":0,"trade":0,"nft":0,"gas":0,"bal":0,"days":0,"spread":0,"streak":0,"rank_m":351386,"pct_m":0.373599},"2023-09":{"txs":0,"uniq":0,"trade":0,"nft":0,"gas":0,"bal":0,"days":0,"spread":0,"streak":0,"rank_m":372570,"pct_m":0.396122},"2023-10":{"txs":0,"uniq":0,"trade":0,"nft":0,"gas":0,"bal":0,"days":0,"spread":0,"streak":0,"rank_m":390640,"pct_m":0.415334},"2023-11":{"txs":0,"uniq":0,"trade":0,"nft":0,"gas":0,"bal":0,"days":0,"spread":0,"streak":0,"rank_m":406881,"pct_m":0.432602},"2023-12":{"txs":0,"uniq":0,"trade":0,"nft":0,"gas":0,"bal":0,"days":0,"spread":0,"streak":0,"rank_m":426952,"pct_m":0.453942},"2024-01":{"txs":0,"uniq":0,"trade":0,"nft":0,"gas":0,"bal":0,"days":0,"spread":0,"streak":0,"rank_m":444100,"pct_m":0.472174},"2024-02":{"txs":0,"uniq":0,"trade":0,"nft":0,"gas":0,"bal":0,"days":0,"spread":0,"streak":0,"rank_m":484408,"pct_m":0.51503},"2024-03":{"txs":0,"uniq":0,"trade":0,"nft":0,"gas":0,"bal":0,"days":0,"spread":0,"streak":0,"rank_m":548227,"pct_m":0.582884},"2024-04":{"txs":0,"uniq":0,"trade":0,"nft":0,"gas":0,"bal":0,"days":0,"spread":0,"streak":0,"rank_m":608847,"pct_m":0.647336},"2024-05":{"txs":0,"uniq":0,"trade":0,"nft":0,"gas":0,"bal":0,"days":0,"spread":0,"streak":0,"rank_m":641009,"pct_m":0.681531},"2024-06":{"txs":0,"uniq":0,"trade":0,"nft":0,"gas":0,"bal":0,"days":0,"spread":0,"streak":0,"rank_m":668267,"pct_m":0.710512},"2024-07":{"txs":0,"uniq":0,"trade":0,"nft":0,"gas":0,"bal":0,"days":0,"spread":0,"streak":0,"rank_m":690463,"pct_m":0.734112},"2024-08":{"txs":0,"uniq":0,"trade":0,"nft":0,"gas":0,"bal":0,"days":0,"spread":0,"streak":0,"rank_m":708973,"pct_m":0.753792},"2024-09":{"txs":0,"uniq":0,"trade":0,"nft":0,"gas":0,"bal":0,"days":0,"spread":0,"streak":0,"rank_m":721335,"pct_m":0.766935},"2024-10":{"txs":0,"uniq":0,"trade":0,"nft":0,"gas":0,"bal":0,"days":0,"spread":0,"streak":0,"rank_m":745336,"pct_m":0.792453},"2024-11":{"txs":0,"uniq":0,"trade":0,"nft":0,"gas":0,"bal":0,"days":0,"spread":0,"streak":0,"rank_m":760273,"pct_m":0.808335},"2024-12":{"txs":0,"uniq":0,"trade":0,"nft":0,"gas":0,"bal":0,"days":0,"spread":0,"streak":0,"rank_m":787037,"pct_m":0.836791},"2025-01":{"txs":0,"uniq":0,"trade":0,"nft":0,"gas":0,"bal":0,"days":0,"spread":0,"streak":0,"rank_m":802794,"pct_m":0.853544},"2025-02":{"txs":0,"uniq":0,"trade":0,"nft":0,"gas":0,"bal":0,"days":0,"spread":0,"streak":0,"rank_m":821923,"pct_m":0.873882},"2025-03":{"txs":0,"uniq":0,"trade":0,"nft":0,"gas":0,"bal":0,"days":0,"spread":0,"streak":0,"rank_m":837426,"pct_m":0.890365},"2025-04":{"txs":90,"uniq":24,"trade":0,"nft":0,"gas":0.000537,"bal":0.000188,"days":12,"spread":0.4,"streak":12,"rank_m":94341,"pct_m":0.100304,"gas_method":"exact"},"2025-05":{"txs":118,"uniq":34,"trade":0,"nft":0,"gas":0.000831,"bal":0.000324,"days":24,"spread":0.774194,"streak":11,"rank_m":234270,"pct_m":0.249079,"gas_method":"estimated"},"2025-06":{"txs":62,"uniq":17,"trade":0,"nft":0,"gas":0.000436,"bal":0.000288,"days":16,"spread":0.533333,"streak":9,"rank_m":302280,"pct_m":0.321388,"gas_method":"estimated"},"2025-07":{"txs":26,"uniq":8,"trade":0,"nft":0,"gas":0.000183,"bal":0.000283,"days":7,"spread":0.225806,"streak":2,"rank_m":415542,"pct_m":0.441811,"gas_method":"estimated"},"2025-08":{"txs":42,"uniq":14,"trade":0,"nft":0,"gas":0.000296,"bal":0.000282,"days":14,"spread":0.451613,"streak":3,"rank_m":322209,"pct_m":0.342577,"gas_method":"estimated"},"2025-09":{"txs":23,"uniq":10,"trade":0,"nft":0,"gas":0.000162,"bal":0.00036,"days":9,"spread":0.3,"streak":4,"rank_m":333741,"pct_m":0.354838,"gas_method":"estimated"},"2025-10":{"txs":6,"uniq":2,"trade":0,"nft":0,"gas":0.000042,"bal":0.000595,"days":3,"spread":0.096774,"streak":1,"rank_m":345411,"pct_m":0.367246,"gas_method":"estimated"}}}