{"wallet":"0xcab866a47e15035daeafc500323b5fa9298e4a99","rank":243303,"lifetime":{"months_active":18,"first":"2023-07","last":"2025-10","tx_sum":294,"uniq_sum":152,"trade_sum":0,"nft_sum":26,"gas_sum":0.001679,"avg_balance_eth_mean":0.002074,"streak_best_days":13,"gas_sum_filled":0.001679},"months":{"2023-07":{"txs":0,"uniq":0,"trade":0,"nft":0,"gas":0,"bal":0,"days":0,"spread":0,"streak":0,"rank_m":236511,"pct_m":0.251462},"2023-08":{"txs":0,"uniq":0,"trade":0,"nft":0,"gas":0,"bal":0,"days":0,"spread":0,"streak":0,"rank_m":327168,"pct_m":0.34785},"2023-09":{"txs":0,"uniq":0,"trade":0,"nft":0,"gas":0,"bal":0,"days":0,"spread":0,"streak":0,"rank_m":345971,"pct_m":0.367841},"2023-10":{"txs":0,"uniq":0,"trade":0,"nft":0,"gas":0,"bal":0,"days":0,"spread":0,"streak":0,"rank_m":364259,"pct_m":0.387286},"2023-11":{"txs":0,"uniq":0,"trade":0,"nft":0,"gas":0,"bal":0,"days":0,"spread":0,"streak":0,"rank_m":380842,"pct_m":0.404917},"2023-12":{"txs":0,"uniq":0,"trade":0,"nft":0,"gas":0,"bal":0,"days":0,"spread":0,"streak":0,"rank_m":402097,"pct_m":0.427516},"2024-01":{"txs":0,"uniq":0,"trade":0,"nft":0,"gas":0,"bal":0,"days":0,"spread":0,"streak":0,"rank_m":419411,"pct_m":0.445924},"2024-02":{"txs":0,"uniq":0,"trade":0,"nft":0,"gas":0,"bal":0,"days":0,"spread":0,"streak":0,"rank_m":462756,"pct_m":0.492009},"2024-03":{"txs":3,"uniq":2,"trade":0,"nft":0,"gas":0.000055,"bal":0.000405,"days":2,"spread":0.064516,"streak":2,"rank_m":326305,"pct_m":0.346932,"gas_method":"estimated"},"2024-04":{"txs":21,"uniq":11,"trade":0,"nft":1,"gas":0.000022,"bal":0.002013,"days":9,"spread":0.3,"streak":3,"rank_m":191754,"pct_m":0.203875,"gas_method":"exact"},"2024-05":{"txs":33,"uniq":16,"trade":0,"nft":2,"gas":0.000025,"bal":0.001799,"days":7,"spread":0.225806,"streak":2,"rank_m":201922,"pct_m":0.214686,"gas_method":"estimated"},"2024-06":{"txs":11,"uniq":6,"trade":0,"nft":1,"gas":0,"bal":0.001677,"days":3,"spread":0.1,"streak":1,"rank_m":322891,"pct_m":0.343302,"gas_method":"estimated"},"2024-07":{"txs":0,"uniq":0,"trade":0,"nft":0,"gas":0,"bal":0.001677,"days":0,"spread":0,"streak":0,"rank_m":527275,"pct_m":0.560607},"2024-08":{"txs":20,"uniq":19,"trade":0,"nft":21,"gas":0.000002,"bal":0.001771,"days":2,"spread":0.064516,"streak":1,"rank_m":242967,"pct_m":0.258326,"gas_method":"estimated"},"2024-09":{"txs":0,"uniq":0,"trade":0,"nft":0,"gas":0,"bal":0.001771,"days":0,"spread":0,"streak":0,"rank_m":516366,"pct_m":0.549008},"2024-10":{"txs":16,"uniq":10,"trade":0,"nft":0,"gas":0.000001,"bal":0.002155,"days":2,"spread":0.064516,"streak":2,"rank_m":305714,"pct_m":0.32504,"gas_method":"estimated"},"2024-11":{"txs":55,"uniq":26,"trade":0,"nft":0,"gas":0.000124,"bal":0.004869,"days":18,"spread":0.6,"streak":13,"rank_m":57990,"pct_m":0.061655,"gas_method":"exact"},"2024-12":{"txs":7,"uniq":1,"trade":0,"nft":0,"gas":0.000154,"bal":0.004026,"days":3,"spread":0.096774,"streak":2,"rank_m":383134,"pct_m":0.407354,"gas_method":"exact"},"2025-01":{"txs":20,"uniq":10,"trade":0,"nft":0,"gas":0.00052,"bal":0.003544,"days":2,"spread":0.064516,"streak":2,"rank_m":231553,"pct_m":0.24619,"gas_method":"exact"},"2025-02":{"txs":14,"uniq":8,"trade":0,"nft":0,"gas":0.000099,"bal":0.003442,"days":1,"spread":0.035714,"streak":1,"rank_m":248955,"pct_m":0.264692,"gas_method":"exact"},"2025-03":{"txs":28,"uniq":10,"trade":0,"nft":0,"gas":0.000221,"bal":0.003409,"days":2,"spread":0.064516,"streak":2,"rank_m":164158,"pct_m":0.174535,"gas_method":"exact"},"2025-04":{"txs":7,"uniq":5,"trade":0,"nft":0,"gas":0.000042,"bal":0.003342,"days":2,"spread":0.066667,"streak":2,"rank_m":267492,"pct_m":0.284401,"gas_method":"exact"},"2025-05":{"txs":7,"uniq":5,"trade":0,"nft":0,"gas":0.000049,"bal":0.003217,"days":2,"spread":0.064516,"streak":2,"rank_m":266143,"pct_m":0.282967,"gas_method":"estimated"},"2025-06":{"txs":9,"uniq":6,"trade":0,"nft":0,"gas":0.000063,"bal":0.003231,"days":2,"spread":0.066667,"streak":2,"rank_m":327088,"pct_m":0.347765,"gas_method":"estimated"},"2025-07":{"txs":14,"uniq":5,"trade":0,"nft":0,"gas":0.000099,"bal":0.003206,"days":2,"spread":0.064516,"streak":2,"rank_m":335786,"pct_m":0.357013,"gas_method":"estimated"},"2025-08":{"txs":8,"uniq":5,"trade":0,"nft":0,"gas":0.000056,"bal":0.003176,"days":1,"spread":0.032258,"streak":1,"rank_m":360113,"pct_m":0.382878,"gas_method":"estimated"},"2025-09":{"txs":9,"uniq":1,"trade":0,"nft":0,"gas":0.000063,"bal":0.003141,"days":1,"spread":0.033333,"streak":1,"rank_m":386672,"pct_m":0.411116,"gas_method":"estimated"},"2025-10":{"txs":12,"uniq":6,"trade":0,"nft":1,"gas":0.000084,"bal":0.006205,"days":2,"spread":0.064516,"streak":2,"rank_m":107984,"pct_m":0.114809,"gas_method":"estimated"}}}