{"wallet":"0xc78d1dd3883920986056daf57abf4c0082f82a01","rank":372698,"lifetime":{"months_active":3,"first":"2023-07","last":"2025-10","tx_sum":774,"uniq_sum":238,"trade_sum":63,"nft_sum":0,"gas_sum":0.005429,"avg_balance_eth_mean":0.000044,"streak_best_days":40,"gas_sum_filled":0.005429},"months":{"2023-07":{"txs":0,"uniq":0,"trade":0,"nft":0,"gas":0,"bal":0,"days":0,"spread":0,"streak":0,"rank_m":247473,"pct_m":0.263117},"2023-08":{"txs":0,"uniq":0,"trade":0,"nft":0,"gas":0,"bal":0,"days":0,"spread":0,"streak":0,"rank_m":336879,"pct_m":0.358175},"2023-09":{"txs":0,"uniq":0,"trade":0,"nft":0,"gas":0,"bal":0,"days":0,"spread":0,"streak":0,"rank_m":356828,"pct_m":0.379385},"2023-10":{"txs":0,"uniq":0,"trade":0,"nft":0,"gas":0,"bal":0,"days":0,"spread":0,"streak":0,"rank_m":375020,"pct_m":0.398727},"2023-11":{"txs":0,"uniq":0,"trade":0,"nft":0,"gas":0,"bal":0,"days":0,"spread":0,"streak":0,"rank_m":391448,"pct_m":0.416193},"2023-12":{"txs":0,"uniq":0,"trade":0,"nft":0,"gas":0,"bal":0,"days":0,"spread":0,"streak":0,"rank_m":412124,"pct_m":0.438177},"2024-01":{"txs":0,"uniq":0,"trade":0,"nft":0,"gas":0,"bal":0,"days":0,"spread":0,"streak":0,"rank_m":429405,"pct_m":0.45655},"2024-02":{"txs":0,"uniq":0,"trade":0,"nft":0,"gas":0,"bal":0,"days":0,"spread":0,"streak":0,"rank_m":471464,"pct_m":0.501268},"2024-03":{"txs":0,"uniq":0,"trade":0,"nft":0,"gas":0,"bal":0,"days":0,"spread":0,"streak":0,"rank_m":537389,"pct_m":0.571361},"2024-04":{"txs":0,"uniq":0,"trade":0,"nft":0,"gas":0,"bal":0,"days":0,"spread":0,"streak":0,"rank_m":599767,"pct_m":0.637682},"2024-05":{"txs":0,"uniq":0,"trade":0,"nft":0,"gas":0,"bal":0,"days":0,"spread":0,"streak":0,"rank_m":632425,"pct_m":0.672404},"2024-06":{"txs":0,"uniq":0,"trade":0,"nft":0,"gas":0,"bal":0,"days":0,"spread":0,"streak":0,"rank_m":660082,"pct_m":0.70181},"2024-07":{"txs":0,"uniq":0,"trade":0,"nft":0,"gas":0,"bal":0,"days":0,"spread":0,"streak":0,"rank_m":682827,"pct_m":0.725993},"2024-08":{"txs":0,"uniq":0,"trade":0,"nft":0,"gas":0,"bal":0,"days":0,"spread":0,"streak":0,"rank_m":701736,"pct_m":0.746097},"2024-09":{"txs":0,"uniq":0,"trade":0,"nft":0,"gas":0,"bal":0,"days":0,"spread":0,"streak":0,"rank_m":714027,"pct_m":0.759165},"2024-10":{"txs":0,"uniq":0,"trade":0,"nft":0,"gas":0,"bal":0,"days":0,"spread":0,"streak":0,"rank_m":739111,"pct_m":0.785835},"2024-11":{"txs":0,"uniq":0,"trade":0,"nft":0,"gas":0,"bal":0,"days":0,"spread":0,"streak":0,"rank_m":753919,"pct_m":0.801579},"2024-12":{"txs":0,"uniq":0,"trade":0,"nft":0,"gas":0,"bal":0,"days":0,"spread":0,"streak":0,"rank_m":781676,"pct_m":0.831091},"2025-01":{"txs":0,"uniq":0,"trade":0,"nft":0,"gas":0,"bal":0,"days":0,"spread":0,"streak":0,"rank_m":797420,"pct_m":0.84783},"2025-02":{"txs":0,"uniq":0,"trade":0,"nft":0,"gas":0,"bal":0,"days":0,"spread":0,"streak":0,"rank_m":817056,"pct_m":0.868707},"2025-03":{"txs":0,"uniq":0,"trade":0,"nft":0,"gas":0,"bal":0,"days":0,"spread":0,"streak":0,"rank_m":833098,"pct_m":0.885764},"2025-04":{"txs":19,"uniq":8,"trade":2,"nft":0,"gas":0.000115,"bal":0.00006,"days":3,"spread":0.1,"streak":2,"rank_m":243879,"pct_m":0.259295,"gas_method":"exact"},"2025-05":{"txs":343,"uniq":103,"trade":2,"nft":0,"gas":0.002414,"bal":0.000287,"days":28,"spread":0.903226,"streak":15,"rank_m":109559,"pct_m":0.116484,"gas_method":"estimated"},"2025-06":{"txs":412,"uniq":127,"trade":59,"nft":0,"gas":0.0029,"bal":0.000179,"days":25,"spread":0.833333,"streak":25,"rank_m":137140,"pct_m":0.145809,"gas_method":"estimated"},"2025-07":{"txs":0,"uniq":0,"trade":0,"nft":0,"gas":0,"bal":0.000179,"days":0,"spread":0,"streak":0,"rank_m":789683,"pct_m":0.839604},"2025-08":{"txs":0,"uniq":0,"trade":0,"nft":0,"gas":0,"bal":0.000179,"days":0,"spread":0,"streak":0,"rank_m":772034,"pct_m":0.820839},"2025-09":{"txs":0,"uniq":0,"trade":0,"nft":0,"gas":0,"bal":0.000179,"days":0,"spread":0,"streak":0,"rank_m":763342,"pct_m":0.811598},"2025-10":{"txs":0,"uniq":0,"trade":0,"nft":0,"gas":0,"bal":0.000179,"days":0,"spread":0,"streak":0,"rank_m":702054,"pct_m":0.746435}}}