{"wallet":"0xcfdef9d164bb1e83916e30472ce14bb7a81293f1","rank":295577,"lifetime":{"months_active":19,"first":"2023-07","last":"2025-10","tx_sum":477,"uniq_sum":248,"trade_sum":6,"nft_sum":77,"gas_sum":0.001135,"avg_balance_eth_mean":0.001067,"streak_best_days":0,"gas_sum_filled":0.001135},"months":{"2023-07":{"txs":0,"uniq":0,"trade":0,"nft":0,"gas":0,"bal":0,"days":0,"spread":0,"streak":0,"rank_m":218624,"pct_m":0.232444},"2023-08":{"txs":0,"uniq":0,"trade":0,"nft":0,"gas":0,"bal":0,"days":0,"spread":0,"streak":0,"rank_m":311405,"pct_m":0.33109},"2023-09":{"txs":0,"uniq":0,"trade":0,"nft":0,"gas":0,"bal":0,"days":0,"spread":0,"streak":0,"rank_m":328000,"pct_m":0.348734},"2023-10":{"txs":0,"uniq":0,"trade":0,"nft":0,"gas":0,"bal":0,"days":0,"spread":0,"streak":0,"rank_m":346356,"pct_m":0.368251},"2023-11":{"txs":0,"uniq":0,"trade":0,"nft":0,"gas":0,"bal":0,"days":0,"spread":0,"streak":0,"rank_m":363091,"pct_m":0.386044},"2023-12":{"txs":0,"uniq":0,"trade":0,"nft":0,"gas":0,"bal":0,"days":0,"spread":0,"streak":0,"rank_m":385234,"pct_m":0.409587},"2024-01":{"txs":0,"uniq":0,"trade":0,"nft":0,"gas":0,"bal":0,"days":0,"spread":0,"streak":0,"rank_m":402426,"pct_m":0.427865},"2024-02":{"txs":0,"uniq":0,"trade":0,"nft":0,"gas":0,"bal":0,"days":0,"spread":0,"streak":0,"rank_m":448155,"pct_m":0.476485},"2024-03":{"txs":35,"uniq":18,"trade":0,"nft":11,"gas":0.000208,"bal":0.001428,"days":8,"spread":0.258065,"streak":0,"rank_m":170847,"pct_m":0.181647,"gas_method":"estimated"},"2024-04":{"txs":62,"uniq":34,"trade":1,"nft":18,"gas":0.000046,"bal":0.002449,"days":13,"spread":0.433333,"streak":0,"rank_m":168208,"pct_m":0.178841,"gas_method":"estimated"},"2024-05":{"txs":67,"uniq":29,"trade":2,"nft":8,"gas":0.000016,"bal":0.00208,"days":10,"spread":0.322581,"streak":0,"rank_m":168323,"pct_m":0.178963,"gas_method":"estimated"},"2024-06":{"txs":20,"uniq":11,"trade":0,"nft":3,"gas":0,"bal":0.00134,"days":8,"spread":0.266667,"streak":0,"rank_m":267215,"pct_m":0.284107,"gas_method":"estimated"},"2024-07":{"txs":43,"uniq":22,"trade":0,"nft":10,"gas":0.000002,"bal":0.001862,"days":15,"spread":0.483871,"streak":0,"rank_m":110040,"pct_m":0.116995,"gas_method":"exact"},"2024-08":{"txs":65,"uniq":28,"trade":1,"nft":14,"gas":0.000006,"bal":0.002657,"days":14,"spread":0.451613,"streak":0,"rank_m":81475,"pct_m":0.086625,"gas_method":"exact"},"2024-09":{"txs":32,"uniq":17,"trade":0,"nft":5,"gas":0,"bal":0.002563,"days":11,"spread":0.366667,"streak":0,"rank_m":111822,"pct_m":0.11889,"gas_method":"exact"},"2024-10":{"txs":33,"uniq":14,"trade":2,"nft":8,"gas":0.000014,"bal":0.000618,"days":6,"spread":0.193548,"streak":0,"rank_m":167480,"pct_m":0.178067,"gas_method":"exact"},"2024-11":{"txs":27,"uniq":15,"trade":0,"nft":0,"gas":0.000062,"bal":0.000897,"days":3,"spread":0.1,"streak":0,"rank_m":287044,"pct_m":0.305189,"gas_method":"exact"},"2024-12":{"txs":6,"uniq":5,"trade":0,"nft":0,"gas":0.000132,"bal":0.002332,"days":5,"spread":0.16129,"streak":0,"rank_m":410817,"pct_m":0.436787,"gas_method":"exact"},"2025-01":{"txs":5,"uniq":3,"trade":0,"nft":0,"gas":0.000078,"bal":0.001793,"days":3,"spread":0.096774,"streak":0,"rank_m":459507,"pct_m":0.488555,"gas_method":"exact"},"2025-02":{"txs":2,"uniq":2,"trade":0,"nft":0,"gas":0.000014,"bal":0.001358,"days":1,"spread":0.035714,"streak":0,"rank_m":497346,"pct_m":0.528786,"gas_method":"exact"},"2025-03":{"txs":0,"uniq":0,"trade":0,"nft":0,"gas":0,"bal":0.001358,"days":0,"spread":0,"streak":0,"rank_m":625028,"pct_m":0.66454},"2025-04":{"txs":5,"uniq":4,"trade":0,"nft":0,"gas":0.00003,"bal":0.001296,"days":2,"spread":0.066667,"streak":0,"rank_m":414521,"pct_m":0.440725,"gas_method":"exact"},"2025-05":{"txs":15,"uniq":12,"trade":0,"nft":0,"gas":0.000106,"bal":0.001999,"days":6,"spread":0.193548,"streak":0,"rank_m":273213,"pct_m":0.290484,"gas_method":"estimated"},"2025-06":{"txs":3,"uniq":3,"trade":0,"nft":0,"gas":0.000021,"bal":0.001116,"days":3,"spread":0.1,"streak":0,"rank_m":502083,"pct_m":0.533823,"gas_method":"estimated"},"2025-07":{"txs":11,"uniq":5,"trade":0,"nft":0,"gas":0.000077,"bal":0.000886,"days":5,"spread":0.16129,"streak":0,"rank_m":464518,"pct_m":0.493883,"gas_method":"estimated"},"2025-08":{"txs":38,"uniq":22,"trade":0,"nft":0,"gas":0.000267,"bal":0.001143,"days":5,"spread":0.16129,"streak":0,"rank_m":329364,"pct_m":0.350185,"gas_method":"estimated"},"2025-09":{"txs":4,"uniq":4,"trade":0,"nft":0,"gas":0.000028,"bal":0.000696,"days":3,"spread":0.1,"streak":0,"rank_m":486949,"pct_m":0.517732,"gas_method":"estimated"},"2025-10":{"txs":4,"uniq":0,"trade":0,"nft":0,"gas":0.000028,"bal":0,"days":1,"spread":0.032258,"streak":0,"rank_m":740768,"pct_m":0.787597,"gas_method":"estimated"}}}