{"wallet":"0xcd958fd6db2899f4e0ab82d90f8259a912a2ae9a","rank":629303,"lifetime":{"months_active":15,"first":"2023-07","last":"2025-10","tx_sum":211,"uniq_sum":61,"trade_sum":1,"nft_sum":7,"gas_sum":0.002192,"avg_balance_eth_mean":0.000691,"streak_best_days":0,"gas_sum_filled":0.002192},"months":{"2023-07":{"txs":0,"uniq":0,"trade":0,"nft":0,"gas":0,"bal":0,"days":0,"spread":0,"streak":0,"rank_m":226716,"pct_m":0.241047},"2023-08":{"txs":6,"uniq":4,"trade":0,"nft":2,"gas":0.000278,"bal":0.0002,"days":2,"spread":0.064516,"streak":0,"rank_m":149628,"pct_m":0.159086,"gas_method":"exact"},"2023-09":{"txs":0,"uniq":0,"trade":0,"nft":0,"gas":0,"bal":0.0002,"days":0,"spread":0,"streak":0,"rank_m":192406,"pct_m":0.204568},"2023-10":{"txs":1,"uniq":1,"trade":0,"nft":0,"gas":0.000006,"bal":0.000808,"days":1,"spread":0.032258,"streak":0,"rank_m":156794,"pct_m":0.166705,"gas_method":"estimated"},"2023-11":{"txs":0,"uniq":0,"trade":0,"nft":0,"gas":0,"bal":0.000808,"days":0,"spread":0,"streak":0,"rank_m":185086,"pct_m":0.196786},"2023-12":{"txs":0,"uniq":0,"trade":0,"nft":0,"gas":0,"bal":0.000808,"days":0,"spread":0,"streak":0,"rank_m":210605,"pct_m":0.223918},"2024-01":{"txs":0,"uniq":0,"trade":0,"nft":0,"gas":0,"bal":0.000808,"days":0,"spread":0,"streak":0,"rank_m":221279,"pct_m":0.235267},"2024-02":{"txs":3,"uniq":1,"trade":0,"nft":0,"gas":0.000031,"bal":0.000193,"days":2,"spread":0.068966,"streak":0,"rank_m":280418,"pct_m":0.298144,"gas_method":"estimated"},"2024-03":{"txs":33,"uniq":11,"trade":0,"nft":1,"gas":0.000516,"bal":0.005402,"days":10,"spread":0.322581,"streak":0,"rank_m":162331,"pct_m":0.172592,"gas_method":"estimated"},"2024-04":{"txs":10,"uniq":8,"trade":0,"nft":1,"gas":0.000019,"bal":0.009176,"days":6,"spread":0.2,"streak":0,"rank_m":293665,"pct_m":0.312229,"gas_method":"estimated"},"2024-05":{"txs":6,"uniq":5,"trade":1,"nft":3,"gas":0.000004,"bal":0.000199,"days":3,"spread":0.096774,"streak":0,"rank_m":402923,"pct_m":0.428394,"gas_method":"estimated"},"2024-06":{"txs":8,"uniq":5,"trade":0,"nft":0,"gas":0,"bal":0.000501,"days":2,"spread":0.066667,"streak":0,"rank_m":456779,"pct_m":0.485655,"gas_method":"estimated"},"2024-07":{"txs":3,"uniq":2,"trade":0,"nft":0,"gas":0,"bal":0.000132,"days":2,"spread":0.064516,"streak":0,"rank_m":509105,"pct_m":0.541288,"gas_method":"estimated"},"2024-08":{"txs":4,"uniq":2,"trade":0,"nft":0,"gas":0,"bal":0.000072,"days":2,"spread":0.064516,"streak":0,"rank_m":530022,"pct_m":0.563528,"gas_method":"estimated"},"2024-09":{"txs":13,"uniq":2,"trade":0,"nft":0,"gas":0,"bal":0,"days":5,"spread":0.166667,"streak":0,"rank_m":473060,"pct_m":0.502965,"gas_method":"estimated"},"2024-10":{"txs":2,"uniq":1,"trade":0,"nft":0,"gas":0,"bal":0,"days":2,"spread":0.064516,"streak":0,"rank_m":598653,"pct_m":0.636498,"gas_method":"estimated"},"2024-11":{"txs":5,"uniq":5,"trade":0,"nft":0,"gas":0.000011,"bal":0.000009,"days":3,"spread":0.1,"streak":0,"rank_m":461631,"pct_m":0.490813,"gas_method":"exact"},"2024-12":{"txs":45,"uniq":6,"trade":0,"nft":0,"gas":0.000904,"bal":0.000013,"days":7,"spread":0.225806,"streak":0,"rank_m":347018,"pct_m":0.368955,"gas_method":"exact"},"2025-01":{"txs":0,"uniq":0,"trade":0,"nft":0,"gas":0,"bal":0.000013,"days":0,"spread":0,"streak":0,"rank_m":720116,"pct_m":0.765639},"2025-02":{"txs":2,"uniq":2,"trade":0,"nft":0,"gas":0,"bal":0,"days":2,"spread":0.071429,"streak":0,"rank_m":574848,"pct_m":0.611188,"gas_method":"exact"},"2025-03":{"txs":0,"uniq":0,"trade":0,"nft":0,"gas":0,"bal":0,"days":0,"spread":0,"streak":0,"rank_m":806439,"pct_m":0.857419},"2025-04":{"txs":70,"uniq":6,"trade":0,"nft":0,"gas":0.000423,"bal":0,"days":3,"spread":0.1,"streak":0,"rank_m":343506,"pct_m":0.365221,"gas_method":"exact"},"2025-05":{"txs":0,"uniq":0,"trade":0,"nft":0,"gas":0,"bal":0,"days":0,"spread":0,"streak":0,"rank_m":865092,"pct_m":0.91978},"2025-06":{"txs":0,"uniq":0,"trade":0,"nft":0,"gas":0,"bal":0,"days":0,"spread":0,"streak":0,"rank_m":878237,"pct_m":0.933756},"2025-07":{"txs":0,"uniq":0,"trade":0,"nft":0,"gas":0,"bal":0,"days":0,"spread":0,"streak":0,"rank_m":899599,"pct_m":0.956469},"2025-08":{"txs":0,"uniq":0,"trade":0,"nft":0,"gas":0,"bal":0,"days":0,"spread":0,"streak":0,"rank_m":901857,"pct_m":0.958869},"2025-09":{"txs":0,"uniq":0,"trade":0,"nft":0,"gas":0,"bal":0,"days":0,"spread":0,"streak":0,"rank_m":903598,"pct_m":0.96072},"2025-10":{"txs":0,"uniq":0,"trade":0,"nft":0,"gas":0,"bal":0,"days":0,"spread":0,"streak":0,"rank_m":881581,"pct_m":0.937312}}}