{"wallet":"0xcd629a1aae70760e5a96921a9d07bc02e63a142a","rank":921248,"lifetime":{"months_active":2,"first":"2023-07","last":"2025-10","tx_sum":171,"uniq_sum":59,"trade_sum":0,"nft_sum":0,"gas_sum":0.001203,"avg_balance_eth_mean":0.000053,"streak_best_days":9,"gas_sum_filled":0.001203},"months":{"2023-07":{"txs":0,"uniq":0,"trade":0,"nft":0,"gas":0,"bal":0,"days":0,"spread":0,"streak":0,"rank_m":227400,"pct_m":0.241775},"2023-08":{"txs":0,"uniq":0,"trade":0,"nft":0,"gas":0,"bal":0,"days":0,"spread":0,"streak":0,"rank_m":319179,"pct_m":0.339356},"2023-09":{"txs":0,"uniq":0,"trade":0,"nft":0,"gas":0,"bal":0,"days":0,"spread":0,"streak":0,"rank_m":336875,"pct_m":0.35817},"2023-10":{"txs":0,"uniq":0,"trade":0,"nft":0,"gas":0,"bal":0,"days":0,"spread":0,"streak":0,"rank_m":355223,"pct_m":0.377678},"2023-11":{"txs":0,"uniq":0,"trade":0,"nft":0,"gas":0,"bal":0,"days":0,"spread":0,"streak":0,"rank_m":371903,"pct_m":0.395413},"2023-12":{"txs":0,"uniq":0,"trade":0,"nft":0,"gas":0,"bal":0,"days":0,"spread":0,"streak":0,"rank_m":393644,"pct_m":0.418528},"2024-01":{"txs":0,"uniq":0,"trade":0,"nft":0,"gas":0,"bal":0,"days":0,"spread":0,"streak":0,"rank_m":410932,"pct_m":0.436909},"2024-02":{"txs":0,"uniq":0,"trade":0,"nft":0,"gas":0,"bal":0,"days":0,"spread":0,"streak":0,"rank_m":455399,"pct_m":0.484187},"2024-03":{"txs":0,"uniq":0,"trade":0,"nft":0,"gas":0,"bal":0,"days":0,"spread":0,"streak":0,"rank_m":524134,"pct_m":0.557268},"2024-04":{"txs":0,"uniq":0,"trade":0,"nft":0,"gas":0,"bal":0,"days":0,"spread":0,"streak":0,"rank_m":588766,"pct_m":0.625985},"2024-05":{"txs":0,"uniq":0,"trade":0,"nft":0,"gas":0,"bal":0,"days":0,"spread":0,"streak":0,"rank_m":621953,"pct_m":0.66127},"2024-06":{"txs":0,"uniq":0,"trade":0,"nft":0,"gas":0,"bal":0,"days":0,"spread":0,"streak":0,"rank_m":650114,"pct_m":0.691212},"2024-07":{"txs":0,"uniq":0,"trade":0,"nft":0,"gas":0,"bal":0,"days":0,"spread":0,"streak":0,"rank_m":673576,"pct_m":0.716157},"2024-08":{"txs":0,"uniq":0,"trade":0,"nft":0,"gas":0,"bal":0,"days":0,"spread":0,"streak":0,"rank_m":692993,"pct_m":0.736801},"2024-09":{"txs":0,"uniq":0,"trade":0,"nft":0,"gas":0,"bal":0,"days":0,"spread":0,"streak":0,"rank_m":705070,"pct_m":0.749642},"2024-10":{"txs":0,"uniq":0,"trade":0,"nft":0,"gas":0,"bal":0,"days":0,"spread":0,"streak":0,"rank_m":731457,"pct_m":0.777697},"2024-11":{"txs":0,"uniq":0,"trade":0,"nft":0,"gas":0,"bal":0,"days":0,"spread":0,"streak":0,"rank_m":746052,"pct_m":0.793215},"2024-12":{"txs":0,"uniq":0,"trade":0,"nft":0,"gas":0,"bal":0,"days":0,"spread":0,"streak":0,"rank_m":775116,"pct_m":0.824116},"2025-01":{"txs":0,"uniq":0,"trade":0,"nft":0,"gas":0,"bal":0,"days":0,"spread":0,"streak":0,"rank_m":790812,"pct_m":0.840804},"2025-02":{"txs":0,"uniq":0,"trade":0,"nft":0,"gas":0,"bal":0,"days":0,"spread":0,"streak":0,"rank_m":811206,"pct_m":0.862488},"2025-03":{"txs":0,"uniq":0,"trade":0,"nft":0,"gas":0,"bal":0,"days":0,"spread":0,"streak":0,"rank_m":827685,"pct_m":0.880008},"2025-04":{"txs":0,"uniq":0,"trade":0,"nft":0,"gas":0,"bal":0,"days":0,"spread":0,"streak":0,"rank_m":854206,"pct_m":0.908206},"2025-05":{"txs":137,"uniq":46,"trade":0,"nft":0,"gas":0.000964,"bal":0.000295,"days":24,"spread":0.774194,"streak":9,"rank_m":239754,"pct_m":0.25491,"gas_method":"estimated"},"2025-06":{"txs":34,"uniq":13,"trade":0,"nft":0,"gas":0.000239,"bal":0.000235,"days":9,"spread":0.3,"streak":3,"rank_m":394419,"pct_m":0.419352,"gas_method":"estimated"},"2025-07":{"txs":0,"uniq":0,"trade":0,"nft":0,"gas":0,"bal":0.000235,"days":0,"spread":0,"streak":0,"rank_m":768610,"pct_m":0.817199},"2025-08":{"txs":0,"uniq":0,"trade":0,"nft":0,"gas":0,"bal":0.000235,"days":0,"spread":0,"streak":0,"rank_m":747923,"pct_m":0.795204},"2025-09":{"txs":0,"uniq":0,"trade":0,"nft":0,"gas":0,"bal":0.000235,"days":0,"spread":0,"streak":0,"rank_m":734717,"pct_m":0.781163},"2025-10":{"txs":0,"uniq":0,"trade":0,"nft":0,"gas":0,"bal":0.000235,"days":0,"spread":0,"streak":0,"rank_m":659308,"pct_m":0.700987}}}