{"wallet":"0xc0cbdfa040dc0da173d52e00fbaf9f90b736533e","rank":216216,"lifetime":{"months_active":20,"first":"2023-07","last":"2025-10","tx_sum":207,"uniq_sum":143,"trade_sum":4,"nft_sum":102,"gas_sum":0.002693,"avg_balance_eth_mean":0.004886,"streak_best_days":5,"gas_sum_filled":0.002693},"months":{"2023-07":{"txs":0,"uniq":0,"trade":0,"nft":0,"gas":0,"bal":0,"days":0,"spread":0,"streak":0,"rank_m":270775,"pct_m":0.287892},"2023-08":{"txs":6,"uniq":6,"trade":0,"nft":5,"gas":0.000729,"bal":0.003413,"days":3,"spread":0.096774,"streak":3,"rank_m":81606,"pct_m":0.086764,"gas_method":"exact"},"2023-09":{"txs":19,"uniq":11,"trade":2,"nft":4,"gas":0.001116,"bal":0.006238,"days":8,"spread":0.266667,"streak":3,"rank_m":16843,"pct_m":0.017907,"gas_method":"exact"},"2023-10":{"txs":7,"uniq":5,"trade":2,"nft":1,"gas":0.000019,"bal":0.003072,"days":5,"spread":0.16129,"streak":2,"rank_m":39879,"pct_m":0.042399,"gas_method":"exact"},"2023-11":{"txs":8,"uniq":5,"trade":0,"nft":0,"gas":0.000067,"bal":0.00257,"days":3,"spread":0.1,"streak":2,"rank_m":54210,"pct_m":0.057636,"gas_method":"exact"},"2023-12":{"txs":9,"uniq":4,"trade":0,"nft":1,"gas":0.000246,"bal":0.004701,"days":4,"spread":0.129032,"streak":1,"rank_m":67054,"pct_m":0.071292,"gas_method":"estimated"},"2024-01":{"txs":2,"uniq":1,"trade":0,"nft":0,"gas":0.000051,"bal":0.006094,"days":2,"spread":0.064516,"streak":2,"rank_m":129082,"pct_m":0.137241,"gas_method":"estimated"},"2024-02":{"txs":9,"uniq":7,"trade":0,"nft":3,"gas":0.00013,"bal":0.005528,"days":5,"spread":0.172414,"streak":2,"rank_m":83503,"pct_m":0.088781,"gas_method":"estimated"},"2024-03":{"txs":5,"uniq":4,"trade":0,"nft":0,"gas":0.000108,"bal":0.00672,"days":2,"spread":0.064516,"streak":2,"rank_m":229904,"pct_m":0.244437,"gas_method":"estimated"},"2024-04":{"txs":6,"uniq":4,"trade":0,"nft":0,"gas":0.000016,"bal":0.009808,"days":3,"spread":0.1,"streak":1,"rank_m":328588,"pct_m":0.34936,"gas_method":"estimated"},"2024-05":{"txs":5,"uniq":2,"trade":0,"nft":1,"gas":0.000004,"bal":0.007612,"days":2,"spread":0.064516,"streak":1,"rank_m":342305,"pct_m":0.363944,"gas_method":"estimated"},"2024-06":{"txs":2,"uniq":1,"trade":0,"nft":0,"gas":0,"bal":0.006271,"days":1,"spread":0.033333,"streak":1,"rank_m":404600,"pct_m":0.430177,"gas_method":"estimated"},"2024-07":{"txs":27,"uniq":22,"trade":0,"nft":25,"gas":0.000004,"bal":0.005382,"days":8,"spread":0.258065,"streak":2,"rank_m":90968,"pct_m":0.096718,"gas_method":"estimated"},"2024-08":{"txs":83,"uniq":54,"trade":0,"nft":57,"gas":0.000004,"bal":0.002317,"days":20,"spread":0.645161,"streak":5,"rank_m":26175,"pct_m":0.027829,"gas_method":"exact"},"2024-09":{"txs":5,"uniq":3,"trade":0,"nft":3,"gas":0,"bal":0.005378,"days":3,"spread":0.1,"streak":1,"rank_m":239628,"pct_m":0.254776,"gas_method":"estimated"},"2024-10":{"txs":1,"uniq":1,"trade":0,"nft":1,"gas":0,"bal":0.00641,"days":1,"spread":0.032258,"streak":1,"rank_m":384162,"pct_m":0.408447,"gas_method":"estimated"},"2024-11":{"txs":1,"uniq":1,"trade":0,"nft":1,"gas":0.000002,"bal":0.006408,"days":1,"spread":0.033333,"streak":1,"rank_m":394585,"pct_m":0.419529,"gas_method":"exact"},"2024-12":{"txs":4,"uniq":4,"trade":0,"nft":0,"gas":0.000088,"bal":0.011887,"days":1,"spread":0.032258,"streak":1,"rank_m":411855,"pct_m":0.437891,"gas_method":"exact"},"2025-01":{"txs":3,"uniq":3,"trade":0,"nft":0,"gas":0.000078,"bal":0.010866,"days":3,"spread":0.096774,"streak":1,"rank_m":378661,"pct_m":0.402598,"gas_method":"exact"},"2025-02":{"txs":0,"uniq":0,"trade":0,"nft":0,"gas":0,"bal":0.010866,"days":0,"spread":0,"streak":0,"rank_m":554488,"pct_m":0.58954},"2025-03":{"txs":0,"uniq":0,"trade":0,"nft":0,"gas":0,"bal":0.010866,"days":0,"spread":0,"streak":0,"rank_m":533677,"pct_m":0.567414},"2025-04":{"txs":4,"uniq":4,"trade":0,"nft":0,"gas":0.000024,"bal":0.001148,"days":1,"spread":0.033333,"streak":1,"rank_m":406175,"pct_m":0.431851,"gas_method":"exact"},"2025-05":{"txs":0,"uniq":0,"trade":0,"nft":0,"gas":0,"bal":0.001148,"days":0,"spread":0,"streak":0,"rank_m":653828,"pct_m":0.695161},"2025-06":{"txs":0,"uniq":0,"trade":0,"nft":0,"gas":0,"bal":0.001148,"days":0,"spread":0,"streak":0,"rank_m":655692,"pct_m":0.697142},"2025-07":{"txs":1,"uniq":1,"trade":0,"nft":0,"gas":0.000007,"bal":0.00024,"days":1,"spread":0.032258,"streak":1,"rank_m":613313,"pct_m":0.652084,"gas_method":"estimated"},"2025-08":{"txs":0,"uniq":0,"trade":0,"nft":0,"gas":0,"bal":0.00024,"days":0,"spread":0,"streak":0,"rank_m":751799,"pct_m":0.799325},"2025-09":{"txs":0,"uniq":0,"trade":0,"nft":0,"gas":0,"bal":0.00024,"days":0,"spread":0,"streak":0,"rank_m":738555,"pct_m":0.785244},"2025-10":{"txs":0,"uniq":0,"trade":0,"nft":0,"gas":0,"bal":0.00024,"days":0,"spread":0,"streak":0,"rank_m":665409,"pct_m":0.707474}}}